msgpack_asgi/__init__.py
msgpack_asgi/_middleware.py
msgpack_asgi/py.typed
msgpack_asgi-2.0.0.dist-info/licenses/LICENSE
msgpack_asgi-2.0.0.dist-info/METADATA
msgpack_asgi-2.0.0.dist-info/WHEEL
msgpack_asgi-2.0.0.dist-info/top_level.txt
msgpack_asgi-2.0.0.dist-info/RECORD
