Metadata-Version: 2.4
Name: msgpack-asgi
Version: 2.0.0
Summary: Drop-in MessagePack support for ASGI applications and frameworks
Author-email: Florimond Manca <florimond.manca@protonmail.com>
License: MIT
Project-URL: Homepage, https://github.com/florimondmanca/msgpack-asgi
Classifier: Development Status :: 5 - Production/Stable
Classifier: Intended Audience :: Developers
Classifier: Programming Language :: Python :: 3
Classifier: Programming Language :: Python :: 3 :: Only
Classifier: Programming Language :: Python :: 3.9
Classifier: Programming Language :: Python :: 3.10
Classifier: Programming Language :: Python :: 3.11
Classifier: Programming Language :: Python :: 3.12
Classifier: Programming Language :: Python :: 3.13
Requires-Python: >=3.9
License-File: LICENSE
Requires-Dist: msgpack
Requires-Dist: starlette
Dynamic: license-file
